Datapath.v
/***************************************************
* Datapath for GCD calculator
* Shanthanu S Rai(1NCO242) and Varun Pattar(1NCO249)
* November, 9 2018
****************************************************/

module Datapath(
input[N-1:0] P, Q,
input Selp, Selq, Sela, Selb, Ldp, Ldq, Ldr, clk, rst,
output[N-1:0] R,
output eq, gth
);

parameter N = 8;

reg[N-1:0] R;
reg[N-1:0] Pbus, Qbus, ALU;
reg[N-1:0] Abus, Bbus;

//regP
always @ (posedge clk, posedge rst) begin

	if(rst) Pbus <= 0;
	else if (Ldp) begin
		if(Selp) Pbus <= P;
		else Pbus <= ALU;
	end
	
end

//regQ
always @ (posedge clk, posedge rst) begin

	if(rst) Qbus <= 0;
	else if(Ldq) begin
		if(Selp) Qbus <= Q;
		else Qbus <= ALU;
	end

end

//mux a
always @ (Pbus, Qbus, Sela) begin

	if(Sela) Abus = Pbus;
	else Abus = Qbus;

end

//mux b
always @ (Pbus, Qbus, Selb) begin

	if(Selb) Bbus = Qbus;
	else Bbus = Pbus;

end

//alu
always @ (Abus, Bbus) ALU = Abus - Bbus;

//reg R
always @ (posedge clk) begin

	if(Ldr) R <= Pbus;
	else R <= R;
		
end

//comparator
assign eq = (Pbus == Qbus)?1:0;
assign gth = (Pbus > Qbus)?1:0;

endmodule

Control_Unit.v
/***************************************************
* Control Unit for GCD calculator
* Shanthanu S Rai(17CO242) and Varun Pattar(17CO249)
* November, 3 2018
****************************************************/

module Control_Unit(
input eq, gth, clk, rst, start,
output Selp, Selq, Sela, Selb, Ldp, Ldq, Ldr, valid,
output[1:0] State_Y
);

parameter N = 8;

reg[N-1:0] Control_Variable;
//y is the current state, Y is the next state
reg[1:0] y, Y;
wire Selp, Selq, Sela, Selb, Ldp, Ldq, Ldr, valid;

parameter S0 = 0, S1 = 1, S2 = 2, S3 = 3;
 
//next state logic
always @ (y, start, eq, gth) begin
	
	case(y)
		S0: if(!start) Y = S0;
			else if(eq) Y = S1;
			else if(gth) Y = S2;
			else Y = S3;
		S1: Y = S0;
		S2: if(eq) Y = S1;
			else if(gth) Y = S2;
			else Y = S3;
		S3:	if(eq) Y = S1;
			else if(gth) Y = S2;
			else Y = S3;
	endcase
	
end

//state register
always @ (posedge rst, negedge clk)
	if(rst) y<=S0;
	else y<=Y;
	
//Assign Control_Variable wires
assign {Selp, Selq, Sela, Selb, Ldp, Ldq, Ldr, valid} = Control_Variable;

//output logic

always @ (y)
	case(y)
		S0: Control_Variable = 8'b11001100;
		S1: Control_Variable = 8'b00000011;
		S2: Control_Variable = 8'b00111000;
		S3: Control_Variable = 8'b00000100;
	endcase
	
assign State_Y = Y;

endmodule

GCD_Calculator.v
/***************************************************
* GCD calculator
* Shanthanu S Rai(17CO242) and Varun Pattar(17CO249)
* November, 13 2018
****************************************************/

`include "Control_Unit.v"
`include "Datapath.v"

module GCD_Calculator(
input[N-1:0] P, Q,
input clk, rst, start,
output[N-1:0] R,
output valid,
output[1:0] State_Y
);

parameter N = 8;

wire Selp, Selq, Sela, Selb, Ldp, Ldq, Ldr, valid, eq, gth;

Control_Unit C(eq, gth, clk, rst, start, Selp, Selq, Sela, Selb, Ldp, Ldq, Ldr, valid, State_Y);

Datapath D(P, Q, Selp, Selq, Sela, Selb, Ldp, Ldq, Ldr, clk, rst, R, eq, gth);

endmodule

t_GCD_Calculator.v
/***************************************************
* GCD calculator
* Shanthanu S Rai(17CO242) and Varun Pattar(17CO249)
* November, 13 2018
****************************************************/

`include "GCD_Calculator.v"

module t_GCD_Calculator;

parameter N = 8;

reg[N-1:0] P, Q;
reg clk, rst, start;
wire[N-1:0] R;
wire valid;
wire[1:0] State_Y;

GCD_Calculator G(P, Q, clk, rst, start, R, valid, State_Y);

always  #10 clk = ~clk;

initial begin
	
	$monitor($time, " rst = %d, State_Y = %d, P = %d, Q = %d, start = %d, clk = %d, R = %d, valid = %d", rst, State_Y, P, Q, start, clk, R, valid);
	clk = 0;
	rst = 1;
	#10 P = 24 ; Q = 13;
	rst = 0;
	#5 start = 1;
	#25 start = 0;
	#500 $finish;	
	
end

initial begin
	$dumpfile("t_GCD_Calculator.vcd");
	$dumpvars(0, t_GCD_Calculator);
end

endmodule

t_GCD_Calculator.vcd
$date
	Tue Nov 13 14:27:21 2018
$end
$version
	Icarus Verilog
$end
$timescale
	1s
$end
$scope module t_GCD_Calculator $end
$var wire 1 ! valid $end
$var wire 2 " State_Y [1:0] $end
$var wire 8 # R [7:0] $end
$var reg 8 $ P [7:0] $end
$var reg 8 % Q [7:0] $end
$var reg 1 & clk $end
$var reg 1 ' rst $end
$var reg 1 ( start $end
$scope module G $end
$var wire 8 ) P [7:0] $end
$var wire 8 * Q [7:0] $end
$var wire 1 & clk $end
$var wire 1 ' rst $end
$var wire 1 ( start $end
$var wire 1 ! valid $end
$var wire 1 + gth $end
$var wire 1 , eq $end
$var wire 2 - State_Y [1:0] $end
$var wire 1 . Selq $end
$var wire 1 / Selp $end
$var wire 1 0 Selb $end
$var wire 1 1 Sela $end
$var wire 8 2 R [7:0] $end
$var wire 1 3 Ldr $end
$var wire 1 4 Ldq $end
$var wire 1 5 Ldp $end
$scope module C $end
$var wire 2 6 State_Y [1:0] $end
$var wire 1 & clk $end
$var wire 1 ' rst $end
$var wire 1 ( start $end
$var wire 1 ! valid $end
$var wire 1 + gth $end
$var wire 1 , eq $end
$var wire 1 . Selq $end
$var wire 1 / Selp $end
$var wire 1 0 Selb $end
$var wire 1 1 Sela $end
$var wire 1 3 Ldr $end
$var wire 1 4 Ldq $end
$var wire 1 5 Ldp $end
$var reg 8 7 Control_Variable [7:0] $end
$var reg 2 8 Y [1:0] $end
$var reg 2 9 y [1:0] $end
$upscope $end
$scope module D $end
$var wire 1 5 Ldp $end
$var wire 1 4 Ldq $end
$var wire 1 3 Ldr $end
$var wire 8 : P [7:0] $end
$var wire 8 ; Q [7:0] $end
$var wire 1 1 Sela $end
$var wire 1 0 Selb $end
$var wire 1 / Selp $end
$var wire 1 . Selq $end
$var wire 1 & clk $end
$var wire 1 ' rst $end
$var wire 1 + gth $end
$var wire 1 , eq $end
$var reg 8 < ALU [7:0] $end
$var reg 8 = Abus [7:0] $end
$var reg 8 > Bbus [7:0] $end
$var reg 8 ? Pbus [7:0] $end
$var reg 8 @ Qbus [7:0] $end
$var reg 8 A R [7:0] $end
$upscope $end
$upscope $end
$upscope $end
$enddefinitions $end
#0
$dumpvars
bx A
b0 @
b0 ?
b0 >
b0 =
b0 <
bx ;
bx :
b0 9
b1 8
b11001100 7
b1 6
15
14
03
bx 2
01
00
1/
1.
b1 -
1,
0+
bx *
bx )
x(
1'
0&
bx %
bx $
bx #
b1 "
0!
$end
#10
b10 "
b10 -
b10 6
b10 8
b11110101 <
0,
1+
b11000 >
b1101 =
b1101 @
b11000 ?
0'
b1101 %
b1101 *
b1101 ;
b11000 $
b11000 )
b11000 :
1&
#15
1(
#20
b1011 <
b11000 =
b1101 >
0/
0.
11
10
04
b111000 7
b10 9
0&
#30
b11 "
b11 -
b11 6
b11 8
b11111110 <
0+
b1011 =
b1011 ?
1&
#40
b10 <
b1101 =
b1011 >
01
00
05
14
b100 7
b11 9
0&
0(
#50
b10 "
b10 -
b10 6
b10 8
b11110111 <
1+
b10 =
b10 @
1&
#60
b1001 <
b1011 =
b10 >
11
10
15
04
b111000 7
b10 9
0&
#70
b111 <
b1001 =
b1001 ?
1&
#80
0&
#90
b101 <
b111 =
b111 ?
1&
#100
0&
#110
b11 <
b101 =
b101 ?
1&
#120
0&
#130
b1 <
b11 =
b11 ?
1&
#140
0&
#150
b11 "
b11 -
b11 6
b11 8
b11111111 <
0+
b1 =
b1 ?
1&
#160
b1 <
b10 =
b1 >
01
00
05
14
b100 7
b11 9
0&
#170
b1 "
b1 -
b1 6
b1 8
b0 <
1,
b1 =
b1 @
1&
#180
04
13
1!
b11 7
b0 "
b0 -
b0 6
b0 8
b1 9
0&
#190
b1 #
b1 2
b1 A
1&
#200
1/
1.
15
14
03
0!
b11001100 7
b0 9
0&
#210
b11110101 <
0,
1+
b11000 >
b1101 =
b1101 @
b11000 ?
1&
